{"totalSegments": 6, "scale": 1.5162458777994936, "same_scale": true, "totalArms_Segment": [1, 1, 1, 1, 1], "same_theta": true, "theta": [24.482297506133524], "phi": 176.3460915662189, "same_material": true, "r": 0.8926885923741793, "g": 0.2798323341849679, "b": 0.5893876427621341, "a": 0.99487596970731, "metallic": 0.3029681566346001, "smoothness": 0.9514541803926988, "DirectionalLightTheta": 0.18682695402007066, "DirectionalLightIntensity": 1.6726338605668, "totalPointLights": 0, "PointLightsRadius": null, "PointLightsPhi": null, "PointLightsTheta": null, "PointLightsIntensity": null, "PointLightsRange": null, "PointLightsColor_r": null, "PointLightsColor_g": null, "PointLightsColor_b": null, "PointLightsColor_a": null, "same_PointLightsColor": null, "totalSpotLights": 0, "SpotLightsRadius": null, "SpotLightsPhi": null, "SpotLightsTheta": null, "SpotLightsIntensity": null, "SpotLightsRange": null, "SpotLightsColor_r": null, "SpotLightsColor_g": null, "SpotLightsColor_b": null, "SpotLightsColor_a": null, "same_SpotLightsColor": null, "SpotAngle": null, "CameraRes_width": 640, "CameraRes_height": 480, "Camera_FieldofView": 80, "CameraRadius": 13, "CameraTheta": 90, "CameraPhi": 0, "CameraVerticalOffset": 0}